setup.py
ghanshyam_indian_states_25/__init__.py
ghanshyam_indian_states_25/asgi.py
ghanshyam_indian_states_25/settings.py
ghanshyam_indian_states_25/urls.py
ghanshyam_indian_states_25/wsgi.py
ghanshyam_indian_states_25.egg-info/PKG-INFO
ghanshyam_indian_states_25.egg-info/SOURCES.txt
ghanshyam_indian_states_25.egg-info/dependency_links.txt
ghanshyam_indian_states_25.egg-info/requires.txt
ghanshyam_indian_states_25.egg-info/top_level.txt
gst1/__init__.py
gst1/admin.py
gst1/apps.py
gst1/fields.py
gst1/forms.py
gst1/models.py
gst1/states.py
gst1/tests.py
gst1/views.py
gst1/migrations/__init__.py