Metadata-Version: 2.1
Name: ghanshyam_indian_states_25
Version: 0.1
Summary: A Django app that provides Indian state choices as a model and form field.
Author: ghanshyam
Author-email: shyamahire19@gmail.com
Classifier: Framework :: Django
Classifier: Programming Language :: Python :: 3
Classifier: Programming Language :: Python :: 3.6
Classifier: Programming Language :: Python :: 3.7
Classifier: Programming Language :: Python :: 3.8
Classifier: Programming Language :: Python :: 3.9
Classifier: Programming Language :: Python :: 3.10
Classifier: Programming Language :: Python :: 3.11
Requires-Dist: django
